gpucrate/__init__.py
gpucrate/cli.py
gpucrate/config.py
gpucrate/exception.py
gpucrate/ldconfig.py
gpucrate/logger.py
gpucrate/readelf.py
gpucrate/utils.py
gpucrate/volume.py
gpucrate/tests/__init__.py
gpucrate/tests/test_cli.py
gpucrate/tests/test_config.py
gpucrate/tests/test_ldconfig.py
gpucrate/tests/test_logging.py
gpucrate/tests/test_readelf.py
gpucrate/tests/test_utils.py
gpucrate/tests/utils.py
gpucrate/tests/data/__init__.py
gpucrate/tests/data/__init__.pyc
gpucrate/tests/data/ldcache.txt
gpucrate/tests/data/ldd.txt
gpucrate/tests/data/readelf.txt
gpucrate-0.1.0.dist-info/DESCRIPTION.rst
gpucrate-0.1.0.dist-info/METADATA
gpucrate-0.1.0.dist-info/RECORD
gpucrate-0.1.0.dist-info/WHEEL
gpucrate-0.1.0.dist-info/entry_points.txt
gpucrate-0.1.0.dist-info/metadata.json
gpucrate-0.1.0.dist-info/pbr.json
gpucrate-0.1.0.dist-info/top_level.txt
