Metadata-Version: 2.0
Name: gpucrate
Version: 0.1.0
Summary: gpucrate creates hard-linked GPU driver volumes for use with docker, singularity, etc.
Home-page: https://github.com/jtriley/gpucrate
Author: Justin Riley
Author-email: UNKNOWN
License: UNKNOWN
Platform: UNKNOWN
Requires-Dist: sh (>=1.11)
Requires-Dist: nvidia-ml-py (>=7.352.0)
Requires-Dist: PyYAML (>=3.11)
